marian_tensorboard/__init__.py
marian_tensorboard/marian_tensorboard.py
marian_tensorboard/version.py
marian_tensorboard-0.2.1.dist-info/LICENSE.md
marian_tensorboard-0.2.1.dist-info/METADATA
marian_tensorboard-0.2.1.dist-info/WHEEL
marian_tensorboard-0.2.1.dist-info/entry_points.txt
marian_tensorboard-0.2.1.dist-info/top_level.txt
marian_tensorboard-0.2.1.dist-info/RECORD
