Metadata-Version: 2.1
Name: marian-tensorboard
Version: 0.2.1
Summary: TensorBoard integration for Marian NMT
Home-page: https://github.com/marian-nmt/marian-tensorboard
Author: Roman Grundkiewicz
Author-email: rgrundkiewicz@gmail.com
License: MIT
Classifier: Development Status :: 4 - Beta
Classifier: Intended Audience :: Developers
Classifier: Intended Audience :: Science/Research
Classifier: Operating System :: POSIX
Classifier: Programming Language :: Python :: 3 :: Only
Classifier: Topic :: Scientific/Engineering
Classifier: Topic :: Scientific/Engineering :: Artificial Intelligence
Classifier: Topic :: Text Processing
Requires-Python: >=3.6
License-File: LICENSE.md
Requires-Dist: protobuf (==3.19)
Requires-Dist: azureml-core (>=1)
Requires-Dist: tensorboard (<3,>=2)
Requires-Dist: tensorboardX (>=2.4)
